filterlist/__init__.py
filterlist/__init__.pyc
filterlist/filterlist.py
filterlist/filterlist.pyc
filterlist-0.0.4.dist-info/DESCRIPTION.rst
filterlist-0.0.4.dist-info/METADATA
filterlist-0.0.4.dist-info/RECORD
filterlist-0.0.4.dist-info/WHEEL
filterlist-0.0.4.dist-info/metadata.json
filterlist-0.0.4.dist-info/top_level.txt
