Metadata-Version: 2.0
Name: filterlist
Version: 0.0.4
Summary: Search list of dictionaries
Home-page: https://github.com/solhuang/filterlist
Author: Solomon Huang
Author-email: huang.solomon@gmail.com
License: UNKNOWN
Platform: UNKNOWN
Classifier: Development Status :: 5 - Production/Stable
Classifier: Intended Audience :: Developers
Classifier: Natural Language :: English
Classifier: License :: OSI Approved :: MIT License
Classifier: Programming Language :: Python
Classifier: Programming Language :: Python :: 2.7
Classifier: Programming Language :: Python :: 3.6
